tidle/__init__.py
tidle/cli.py
tidle/tidle.py
tidle-1.0.7.dist-info/METADATA
tidle-1.0.7.dist-info/WHEEL
tidle-1.0.7.dist-info/entry_points.txt
tidle-1.0.7.dist-info/RECORD
